pyjam/__init__.py
pyjam/cli.py
pyjam/constants.py
pyjam/clients/__init__.py
pyjam/clients/certificate.py
pyjam/clients/cloudfront.py
pyjam/clients/route53.py
pyjam/clients/s3.py
pyjam/utils/__init__.py
pyjam/utils/checksum.py
pyjam/utils/route53.py
pyjam/utils/s3.py
pyjam-0.3.2.dist-info/LICENSE
pyjam-0.3.2.dist-info/METADATA
pyjam-0.3.2.dist-info/WHEEL
pyjam-0.3.2.dist-info/entry_points.txt
pyjam-0.3.2.dist-info/top_level.txt
pyjam-0.3.2.dist-info/RECORD
