Metadata-Version: 2.1
Name: pyjam
Version: 0.3.2
Summary: Pyjam automate static websites deployment to S3.
Home-page: https://github.com/tyh835/pydeploy
Author: Tony Han
Author-email: itony9401@live.com
License: GPLv3+
Keywords: aws s3 route53 dns cdn cloudfront static website management cli
Platform: any
Classifier: Programming Language :: Python :: 3
Classifier: License :: OSI Approved :: GNU General Public License v3 or later (GPLv3+)
Classifier: Operating System :: OS Independent
Requires-Dist: click
Requires-Dist: boto3
